{"base_spec":"/pa/units/generic/orbM.json","display_name":"Buzzer","description":"Orbital hunter drone: fast moving orbital vehicle for attacking unarmed targets.","build_metal_cost":200,"max_health":200,"gravwell_velocity_multiplier":20,"system_velocity_multiplier":20,"spawn_layers":"WL_Orbital","unit_types":["UNITTYPE_Mobile","UNITTYPE_Offense","UNITTYPE_Orbital","UNITTYPE_Fighter","UNITTYPE_Basic","UNITTYPE_Custom1","UNITTYPE_Custom2"],"command_caps":["ORDER_Move","ORDER_Patrol","ORDER_Attack","ORDER_Assist"],"guard_radius":150,"navigation":{"acceleration":10,"brake":30,"move_speed":60,"turn_speed":30,"circle_min_time":0,"circle_max_time":0,"hover_time":-1,"aggressive_distance":20,"bank_factor":1},"physics":{"radius":5,"push_class":15,"gravity_scalar":0.001},"model":{"filename":"/pa/units/orbital/buzzer/buzzer.papa","animations":{"open":"/pa/units/orbital/buzzer/buzzer_anim_open.papa","deploy":"/pa/units/orbital/buzzer/buzzer_anim_deploy.papa"},"animtree":"/pa/units/orbital/buzzer/buzzer_anim_tree.json"},"tools":[{"spec_id":"/pa/units/orbital/buzzer/buzzer_tool_weapon.json","aim_bone":"bone_root","muzzle_bone":"muzzle00"}],"events":{"fired":{"effect_spec":"/pa/effects/specs/fired_lightning.pfx muzzle00"}},"fx_offsets":[{"type":"moving","filename":"/pa/effects/specs/jet_aircraftNT.pfx","bone":"engine00"},{"type":"moving","filename":"/pa/effects/specs/jet_aircraftDot.pfx","bone":"engine00"}],"mesh_bounds":[5.5,11.4,5.5],"TEMP_texelinfo":17.7177}